starmodel/__init__.py
starmodel/persistence.py
starmodel/py.typed
starmodel/state.py
starmodel-0.1.0.dist-info/METADATA
starmodel-0.1.0.dist-info/WHEEL
starmodel-0.1.0.dist-info/RECORD
