Metadata-Version: 2.4
Name: starmodel
Version: 0.1.0
Summary: StarModel - Reactive State Management for FastHTML
Author-email: ndendic <ndendic@gmail.com>
Requires-Python: >=3.12
Requires-Dist: datastar-py==0.4.3
Requires-Dist: python-fasthtml>=0.12.19
Requires-Dist: sqlmodel>=0.0.24
